[{"id":"VacationgFeeZbIU","date":"2019-03-09T18:03:05.649Z","mediaFilename":"VacationgFeeZbIU.jpg","caption":"tag ur self I'm the Vacation","postedToGit":true,"htmlFragment":"<li class=\"pane\">\n  <div class=\"time-stamp entry-meta\">\n    <a href=\"VacationgFeeZbIU.html\">\n      <time datetime=\"2019-03-09T18:03:05.649Z\">2019-3-9 18:03:05</time>\n    </a>\n  </div><img src=\"media/VacationgFeeZbIU.jpg\" alt=\"tag ur self I'm the Vacation\"></video><div class=\"media-caption entry-meta\">tag ur self I'm the Vacation</div></li>","postedSingleVideoPage":true},{"id":"WaterrpJSqrgu","date":"2019-03-09T21:03:07.638Z","mediaFilename":"WaterrpJSqrgu.jpg","caption":"tag ur self I'm the Water","postedToGit":true,"htmlFragment":"<li class=\"pane\">\n  <div class=\"time-stamp entry-meta\">\n    <a href=\"WaterrpJSqrgu.html\">\n      <time datetime=\"2019-03-09T21:03:07.638Z\">2019-3-9 21:03:07</time>\n    </a>\n  </div><img src=\"media/WaterrpJSqrgu.jpg\" alt=\"tag ur self I'm the Water\"></video><div class=\"media-caption entry-meta\">tag ur self I'm the Water</div></li>","postedSingleVideoPage":true},{"id":"Long-hairdbYafmch","date":"2019-03-10T00:03:04.692Z","mediaFilename":"Long-hairdbYafmch.jpg","caption":"tag ur self I'm the Long hair","postedToGit":true,"htmlFragment":"<li class=\"pane\">\n  <div class=\"time-stamp entry-meta\">\n    <a href=\"Long-hairdbYafmch.html\">\n      <time datetime=\"2019-03-10T00:03:04.692Z\">2019-3-10 00:03:04</time>\n    </a>\n  </div><img src=\"media/Long-hairdbYafmch.jpg\" alt=\"tag ur self I'm the Long hair\"></video><div class=\"media-caption entry-meta\">tag ur self I'm the Long hair</div></li>","postedSingleVideoPage":true},{"id":"InterLKUSASjCZBCQc","date":"2019-03-10T03:03:06.145Z","mediaFilename":"InterLKUSASjCZBCQc.jpg","caption":"tag ur self I'm \"InterLKUSA\"","postedToGit":true,"htmlFragment":"<li class=\"pane\">\n  <div class=\"time-stamp entry-meta\">\n    <a href=\"InterLKUSASjCZBCQc.html\">\n      <time datetime=\"2019-03-10T03:03:06.145Z\">2019-3-10 03:03:06</time>\n    </a>\n  </div><img src=\"media/InterLKUSASjCZBCQc.jpg\" alt=\"tag ur self I'm \"InterLKUSA\"\"></video><div class=\"media-caption entry-meta\">tag ur self I'm \"InterLKUSA\"</div></li>","postedSingleVideoPage":true},{"id":"Residential-areaYpAENccy","date":"2019-03-10T06:03:05.936Z","mediaFilename":"Residential-areaYpAENccy.jpg","caption":"tag ur self I'm the Residential area","postedToGit":true,"htmlFragment":"<li class=\"pane\">\n  <div class=\"time-stamp entry-meta\">\n    <a href=\"Residential-areaYpAENccy.html\">\n      <time datetime=\"2019-03-10T06:03:05.936Z\">2019-3-10 06:03:05</time>\n    </a>\n  </div><img src=\"media/Residential-areaYpAENccy.jpg\" alt=\"tag ur self I'm the Residential area\"></video><div class=\"media-caption entry-meta\">tag ur self I'm the Residential area</div></li>","postedSingleVideoPage":true},{"id":"Flower-ArrangingicZvpczG","date":"2019-03-10T09:03:05.856Z","mediaFilename":"Flower-ArrangingicZvpczG.jpg","caption":"tag ur self I'm the Flower Arranging","postedToGit":true,"htmlFragment":"<li class=\"pane\">\n  <div class=\"time-stamp entry-meta\">\n    <a href=\"Flower-ArrangingicZvpczG.html\">\n      <time datetime=\"2019-03-10T09:03:05.856Z\">2019-3-10 09:03:05</time>\n    </a>\n  </div><img src=\"media/Flower-ArrangingicZvpczG.jpg\" alt=\"tag ur self I'm the Flower Arranging\"></video><div class=\"media-caption entry-meta\">tag ur self I'm the Flower Arranging</div></li>","postedSingleVideoPage":true},{"id":"VachaGEPTXZHQ","date":"2019-03-10T12:03:05.847Z","mediaFilename":"VachaGEPTXZHQ.jpg","caption":"tag ur self I'm the Vacha","postedToGit":true,"htmlFragment":"<li class=\"pane\">\n  <div class=\"time-stamp entry-meta\">\n    <a href=\"VachaGEPTXZHQ.html\">\n      <time datetime=\"2019-03-10T12:03:05.847Z\">2019-3-10 12:03:05</time>\n    </a>\n  </div><img src=\"media/VachaGEPTXZHQ.jpg\" alt=\"tag ur self I'm the Vacha\"></video><div class=\"media-caption entry-meta\">tag ur self I'm the Vacha</div></li>","postedSingleVideoPage":true},{"id":"49074bxxvEBKiU","date":"2019-03-10T15:03:04.740Z","mediaFilename":"49074bxxvEBKiU.jpg","caption":"tag ur self I'm \"49074b\"","postedToGit":true,"htmlFragment":"<li class=\"pane\">\n  <div class=\"time-stamp entry-meta\">\n    <a href=\"49074bxxvEBKiU.html\">\n      <time datetime=\"2019-03-10T15:03:04.740Z\">2019-3-10 15:03:04</time>\n    </a>\n  </div><img src=\"media/49074bxxvEBKiU.jpg\" alt=\"tag ur self I'm \"49074b\"\"></video><div class=\"media-caption entry-meta\">tag ur self I'm \"49074b\"</div></li>","postedSingleVideoPage":true},{"id":"WarshipnkEfyhou","date":"2019-03-10T18:03:04.919Z","mediaFilename":"WarshipnkEfyhou.jpg","caption":"tag ur self I'm the Warship","postedToGit":true,"htmlFragment":"<li class=\"pane\">\n  <div class=\"time-stamp entry-meta\">\n    <a href=\"WarshipnkEfyhou.html\">\n      <time datetime=\"2019-03-10T18:03:04.919Z\">2019-3-10 18:03:04</time>\n    </a>\n  </div><img src=\"media/WarshipnkEfyhou.jpg\" alt=\"tag ur self I'm the Warship\"></video><div class=\"media-caption entry-meta\">tag ur self I'm the Warship</div></li>","postedSingleVideoPage":true},{"id":"ParallelMkhKbivj","date":"2019-03-10T21:03:06.067Z","mediaFilename":"ParallelMkhKbivj.jpg","caption":"tag ur self I'm the Parallel","postedToGit":true,"htmlFragment":"<li class=\"pane\">\n  <div class=\"time-stamp entry-meta\">\n    <a href=\"ParallelMkhKbivj.html\">\n      <time datetime=\"2019-03-10T21:03:06.067Z\">2019-3-10 21:03:06</time>\n    </a>\n  </div><img src=\"media/ParallelMkhKbivj.jpg\" alt=\"tag ur self I'm the Parallel\"></video><div class=\"media-caption entry-meta\">tag ur self I'm the Parallel</div></li>","postedSingleVideoPage":true},{"id":"Hindu-templeaRBNFIUD","date":"2019-03-11T00:03:04.892Z","mediaFilename":"Hindu-templeaRBNFIUD.jpg","caption":"tag ur self I'm the Hindu temple","postedToGit":true,"htmlFragment":"<li class=\"pane\">\n  <div class=\"time-stamp entry-meta\">\n    <a href=\"Hindu-templeaRBNFIUD.html\">\n      <time datetime=\"2019-03-11T00:03:04.892Z\">2019-3-11 00:03:04</time>\n    </a>\n  </div><img src=\"media/Hindu-templeaRBNFIUD.jpg\" alt=\"tag ur self I'm the Hindu temple\"></video><div class=\"media-caption entry-meta\">tag ur self I'm the Hindu temple</div></li>","postedSingleVideoPage":true},{"id":"Narrow-body-aircraftdAjziYjx","date":"2019-03-11T03:03:05.673Z","mediaFilename":"Narrow-body-aircraftdAjziYjx.jpg","caption":"tag ur self I'm the Narrow-body aircraft","postedToGit":true,"htmlFragment":"<li class=\"pane\">\n  <div class=\"time-stamp entry-meta\">\n    <a href=\"Narrow-body-aircraftdAjziYjx.html\">\n      <time datetime=\"2019-03-11T03:03:05.673Z\">2019-3-11 03:03:05</time>\n    </a>\n  </div><img src=\"media/Narrow-body-aircraftdAjziYjx.jpg\" alt=\"tag ur self I'm the Narrow-body aircraft\"></video><div class=\"media-caption entry-meta\">tag ur self I'm the Narrow-body aircraft</div></li>","postedSingleVideoPage":true},{"id":"BonfirebqlRxMjU","date":"2019-03-11T06:03:05.455Z","mediaFilename":"BonfirebqlRxMjU.jpg","caption":"tag ur self I'm the Bonfire","postedToGit":true,"htmlFragment":"<li class=\"pane\">\n  <div class=\"time-stamp entry-meta\">\n    <a href=\"BonfirebqlRxMjU.html\">\n      <time datetime=\"2019-03-11T06:03:05.455Z\">2019-3-11 06:03:05</time>\n    </a>\n  </div><img src=\"media/BonfirebqlRxMjU.jpg\" alt=\"tag ur self I'm the Bonfire\"></video><div class=\"media-caption entry-meta\">tag ur self I'm the Bonfire</div></li>","postedSingleVideoPage":true},{"id":"FloorbGrnJOTp","date":"2019-03-11T09:03:05.687Z","mediaFilename":"FloorbGrnJOTp.jpg","caption":"tag ur self I'm the Floor","postedToGit":true,"htmlFragment":"<li class=\"pane\">\n  <div class=\"time-stamp entry-meta\">\n    <a href=\"FloorbGrnJOTp.html\">\n      <time datetime=\"2019-03-11T09:03:05.687Z\">2019-3-11 09:03:05</time>\n    </a>\n  </div><img src=\"media/FloorbGrnJOTp.jpg\" alt=\"tag ur self I'm the Floor\"></video><div class=\"media-caption entry-meta\">tag ur self I'm the Floor</div></li>","postedSingleVideoPage":true},{"id":"CottageXDczXCZB","date":"2019-03-11T12:03:07.249Z","mediaFilename":"CottageXDczXCZB.jpg","caption":"tag ur self I'm the Cottage","postedToGit":true,"htmlFragment":"<li class=\"pane\">\n  <div class=\"time-stamp entry-meta\">\n    <a href=\"CottageXDczXCZB.html\">\n      <time datetime=\"2019-03-11T12:03:07.249Z\">2019-3-11 12:03:07</time>\n    </a>\n  </div><img src=\"media/CottageXDczXCZB.jpg\" alt=\"tag ur self I'm the Cottage\"></video><div class=\"media-caption entry-meta\">tag ur self I'm the Cottage</div></li>","postedSingleVideoPage":true},{"id":"ApartmentcqFyMPhd","date":"2019-03-11T15:03:06.989Z","mediaFilename":"ApartmentcqFyMPhd.jpg","caption":"tag ur self I'm the Apartment","postedToGit":true,"htmlFragment":"<li class=\"pane\">\n  <div class=\"time-stamp entry-meta\">\n    <a href=\"ApartmentcqFyMPhd.html\">\n      <time datetime=\"2019-03-11T15:03:06.989Z\">2019-3-11 15:03:06</time>\n    </a>\n  </div><img src=\"media/ApartmentcqFyMPhd.jpg\" alt=\"tag ur self I'm the Apartment\"></video><div class=\"media-caption entry-meta\">tag ur self I'm the Apartment</div></li>","postedSingleVideoPage":true}]