[{"id":"NatureygihGHqH","date":"2019-05-27T12:03:05.667Z","mediaFilename":"NatureygihGHqH.jpg","caption":"tag ur self I'm the Nature","postedToGit":true,"htmlFragment":"<li class=\"pane\">\n  <div class=\"time-stamp entry-meta\">\n    <a href=\"NatureygihGHqH.html\">\n      <time datetime=\"2019-05-27T12:03:05.667Z\">2019-5-27 12:03:05</time>\n    </a>\n  </div><img src=\"media/NatureygihGHqH.jpg\" alt=\"tag ur self I'm the Nature\"></video><div class=\"media-caption entry-meta\">tag ur self I'm the Nature</div></li>","postedSingleVideoPage":true}]