[{"id":"ViaductZlhAYHFo","date":"2019-06-11T21:03:08.837Z","mediaFilename":"ViaductZlhAYHFo.jpg","caption":"tag ur self I'm the Viaduct","postedToGit":true,"htmlFragment":"<li class=\"pane\">\n  <div class=\"time-stamp entry-meta\">\n    <a href=\"ViaductZlhAYHFo.html\">\n      <time datetime=\"2019-06-11T21:03:08.837Z\">2019-6-11 21:03:08</time>\n    </a>\n  </div><img src=\"media/ViaductZlhAYHFo.jpg\" alt=\"tag ur self I'm the Viaduct\"></video><div class=\"media-caption entry-meta\">tag ur self I'm the Viaduct</div></li>","postedSingleVideoPage":true},{"id":"Stone-wallCnIyqVqn","date":"2019-06-12T00:03:05.260Z","mediaFilename":"Stone-wallCnIyqVqn.jpg","caption":"tag ur self I'm the Stone wall","postedToGit":true,"htmlFragment":"<li class=\"pane\">\n  <div class=\"time-stamp entry-meta\">\n    <a href=\"Stone-wallCnIyqVqn.html\">\n      <time datetime=\"2019-06-12T00:03:05.260Z\">2019-6-12 00:03:05</time>\n    </a>\n  </div><img src=\"media/Stone-wallCnIyqVqn.jpg\" alt=\"tag ur self I'm the Stone wall\"></video><div class=\"media-caption entry-meta\">tag ur self I'm the Stone wall</div></li>","postedSingleVideoPage":true},{"id":"HillhBLKDczu","date":"2019-06-12T03:03:08.610Z","mediaFilename":"HillhBLKDczu.jpg","caption":"tag ur self I'm the Hill","postedToGit":true,"htmlFragment":"<li class=\"pane\">\n  <div class=\"time-stamp entry-meta\">\n    <a href=\"HillhBLKDczu.html\">\n      <time datetime=\"2019-06-12T03:03:08.610Z\">2019-6-12 03:03:08</time>\n    </a>\n  </div><img src=\"media/HillhBLKDczu.jpg\" alt=\"tag ur self I'm the Hill\"></video><div class=\"media-caption entry-meta\">tag ur self I'm the Hill</div></li>","postedSingleVideoPage":true},{"id":"AdaptationqsgWWPQD","date":"2019-06-12T06:03:04.568Z","mediaFilename":"AdaptationqsgWWPQD.jpg","caption":"tag ur self I'm the Adaptation","postedToGit":true,"htmlFragment":"<li class=\"pane\">\n  <div class=\"time-stamp entry-meta\">\n    <a href=\"AdaptationqsgWWPQD.html\">\n      <time datetime=\"2019-06-12T06:03:04.568Z\">2019-6-12 06:03:04</time>\n    </a>\n  </div><img src=\"media/AdaptationqsgWWPQD.jpg\" alt=\"tag ur self I'm the Adaptation\"></video><div class=\"media-caption entry-meta\">tag ur self I'm the Adaptation</div></li>","postedSingleVideoPage":true},{"id":"RidgeSXBQpivS","date":"2019-06-12T09:03:04.815Z","mediaFilename":"RidgeSXBQpivS.jpg","caption":"tag ur self I'm the Ridge","postedToGit":true,"htmlFragment":"<li class=\"pane\">\n  <div class=\"time-stamp entry-meta\">\n    <a href=\"RidgeSXBQpivS.html\">\n      <time datetime=\"2019-06-12T09:03:04.815Z\">2019-6-12 09:03:04</time>\n    </a>\n  </div><img src=\"media/RidgeSXBQpivS.jpg\" alt=\"tag ur self I'm the Ridge\"></video><div class=\"media-caption entry-meta\">tag ur self I'm the Ridge</div></li>","postedSingleVideoPage":true},{"id":"TreeEdrTzmuV","date":"2019-06-12T12:03:05.959Z","mediaFilename":"TreeEdrTzmuV.jpg","caption":"tag ur self I'm the Tree","postedToGit":true,"htmlFragment":"<li class=\"pane\">\n  <div class=\"time-stamp entry-meta\">\n    <a href=\"TreeEdrTzmuV.html\">\n      <time datetime=\"2019-06-12T12:03:05.959Z\">2019-6-12 12:03:05</time>\n    </a>\n  </div><img src=\"media/TreeEdrTzmuV.jpg\" alt=\"tag ur self I'm the Tree\"></video><div class=\"media-caption entry-meta\">tag ur self I'm the Tree</div></li>","postedSingleVideoPage":true},{"id":"NeckaLmdgEpV","date":"2019-06-12T15:03:08.135Z","mediaFilename":"NeckaLmdgEpV.jpg","caption":"tag ur self I'm the Neck","postedToGit":true,"htmlFragment":"<li class=\"pane\">\n  <div class=\"time-stamp entry-meta\">\n    <a href=\"NeckaLmdgEpV.html\">\n      <time datetime=\"2019-06-12T15:03:08.135Z\">2019-6-12 15:03:08</time>\n    </a>\n  </div><img src=\"media/NeckaLmdgEpV.jpg\" alt=\"tag ur self I'm the Neck\"></video><div class=\"media-caption entry-meta\">tag ur self I'm the Neck</div></li>","postedSingleVideoPage":true},{"id":"ParisYsPUZBtS","date":"2019-06-12T18:03:11.893Z","mediaFilename":"ParisYsPUZBtS.jpg","caption":"tag ur self I'm \"Paris\"","postedToGit":true,"htmlFragment":"<li class=\"pane\">\n  <div class=\"time-stamp entry-meta\">\n    <a href=\"ParisYsPUZBtS.html\">\n      <time datetime=\"2019-06-12T18:03:11.893Z\">2019-6-12 18:03:11</time>\n    </a>\n  </div><img src=\"media/ParisYsPUZBtS.jpg\" alt=\"tag ur self I'm \"Paris\"\"></video><div class=\"media-caption entry-meta\">tag ur self I'm \"Paris\"</div></li>","postedSingleVideoPage":true},{"id":"58FLyVEPIA","date":"2019-06-12T21:03:10.652Z","mediaFilename":"58FLyVEPIA.jpg","caption":"tag ur self I'm \"58\"","postedToGit":true,"htmlFragment":"<li class=\"pane\">\n  <div class=\"time-stamp entry-meta\">\n    <a href=\"58FLyVEPIA.html\">\n      <time datetime=\"2019-06-12T21:03:10.652Z\">2019-6-12 21:03:10</time>\n    </a>\n  </div><img src=\"media/58FLyVEPIA.jpg\" alt=\"tag ur self I'm \"58\"\"></video><div class=\"media-caption entry-meta\">tag ur self I'm \"58\"</div></li>","postedSingleVideoPage":true},{"id":"BirdrCRfZriC","date":"2019-06-13T00:03:11.149Z","mediaFilename":"BirdrCRfZriC.jpg","caption":"tag ur self I'm the Bird","postedToGit":true,"htmlFragment":"<li class=\"pane\">\n  <div class=\"time-stamp entry-meta\">\n    <a href=\"BirdrCRfZriC.html\">\n      <time datetime=\"2019-06-13T00:03:11.149Z\">2019-6-13 00:03:11</time>\n    </a>\n  </div><img src=\"media/BirdrCRfZriC.jpg\" alt=\"tag ur self I'm the Bird\"></video><div class=\"media-caption entry-meta\">tag ur self I'm the Bird</div></li>","postedSingleVideoPage":true}]