[{"id":"ebenbxjRfMYX","date":"2018-06-05T15:03:08.494Z","mediaFilename":"ebenbxjRfMYX.jpg","caption":"tag ur self I'm \"eben\"","postedToGit":true,"htmlFragment":"<li class=\"pane\">\n  <div class=\"time-stamp entry-meta\">\n    <a href=\"ebenbxjRfMYX.html\">\n      <time datetime=\"2018-06-05T15:03:08.494Z\">2018-6-5 15:03:08</time>\n    </a>\n  </div><img src=\"media/ebenbxjRfMYX.jpg\" alt=\"tag ur self I'm \"eben\"\"></video><div class=\"media-caption entry-meta\">tag ur self I'm \"eben\"</div></li>","postedSingleVideoPage":true},{"id":"traffichELPIinp","date":"2018-06-05T18:03:06.858Z","mediaFilename":"traffichELPIinp.jpg","caption":"tag ur self I'm the traffic","postedToGit":true,"htmlFragment":"<li class=\"pane\">\n  <div class=\"time-stamp entry-meta\">\n    <a href=\"traffichELPIinp.html\">\n      <time datetime=\"2018-06-05T18:03:06.858Z\">2018-6-5 18:03:06</time>\n    </a>\n  </div><img src=\"media/traffichELPIinp.jpg\" alt=\"tag ur self I'm the traffic\"></video><div class=\"media-caption entry-meta\">tag ur self I'm the traffic</div></li>","postedSingleVideoPage":true},{"id":"significantZOUgzXkc","date":"2018-06-05T21:03:06.056Z","mediaFilename":"significantZOUgzXkc.jpg","caption":"tag ur self I'm \"significant\"","postedToGit":true,"htmlFragment":"<li class=\"pane\">\n  <div class=\"time-stamp entry-meta\">\n    <a href=\"significantZOUgzXkc.html\">\n      <time datetime=\"2018-06-05T21:03:06.056Z\">2018-6-5 21:03:06</time>\n    </a>\n  </div><img src=\"media/significantZOUgzXkc.jpg\" alt=\"tag ur self I'm \"significant\"\"></video><div class=\"media-caption entry-meta\">tag ur self I'm \"significant\"</div></li>","postedSingleVideoPage":true}]