[{"id":"close-upXGrGPfRw","date":"2018-06-29T18:03:05.145Z","mediaFilename":"close-upXGrGPfRw.jpg","caption":"tag ur self I'm the close up","postedToGit":true,"htmlFragment":"<li class=\"pane\">\n  <div class=\"time-stamp entry-meta\">\n    <a href=\"close-upXGrGPfRw.html\">\n      <time datetime=\"2018-06-29T18:03:05.145Z\">2018-6-29 18:03:05</time>\n    </a>\n  </div><img src=\"media/close-upXGrGPfRw.jpg\" alt=\"tag ur self I'm the close up\"></video><div class=\"media-caption entry-meta\">tag ur self I'm the close up</div></li>","postedSingleVideoPage":true},{"id":"automotive-exteriorHwetKVku","date":"2018-06-29T21:03:05.609Z","mediaFilename":"automotive-exteriorHwetKVku.jpg","caption":"tag ur self I'm the automotive exterior","postedToGit":true,"htmlFragment":"<li class=\"pane\">\n  <div class=\"time-stamp entry-meta\">\n    <a href=\"automotive-exteriorHwetKVku.html\">\n      <time datetime=\"2018-06-29T21:03:05.609Z\">2018-6-29 21:03:05</time>\n    </a>\n  </div><img src=\"media/automotive-exteriorHwetKVku.jpg\" alt=\"tag ur self I'm the automotive exterior\"></video><div class=\"media-caption entry-meta\">tag ur self I'm the automotive exterior</div></li>","postedSingleVideoPage":true},{"id":"thoroughfareGHcpCrkF","date":"2018-06-30T00:03:32.205Z","mediaFilename":"thoroughfareGHcpCrkF.jpg","caption":"tag ur self I'm the thoroughfare","postedToGit":true,"htmlFragment":"<li class=\"pane\">\n  <div class=\"time-stamp entry-meta\">\n    <a href=\"thoroughfareGHcpCrkF.html\">\n      <time datetime=\"2018-06-30T00:03:32.205Z\">2018-6-30 00:03:32</time>\n    </a>\n  </div><img src=\"media/thoroughfareGHcpCrkF.jpg\" alt=\"tag ur self I'm the thoroughfare\"></video><div class=\"media-caption entry-meta\">tag ur self I'm the thoroughfare</div></li>","postedSingleVideoPage":true},{"id":"houseFKJcNwRc","date":"2018-06-30T03:03:05.187Z","mediaFilename":"houseFKJcNwRc.jpg","caption":"tag ur self I'm the house","postedToGit":true,"htmlFragment":"<li class=\"pane\">\n  <div class=\"time-stamp entry-meta\">\n    <a href=\"houseFKJcNwRc.html\">\n      <time datetime=\"2018-06-30T03:03:05.187Z\">2018-6-30 03:03:05</time>\n    </a>\n  </div><img src=\"media/houseFKJcNwRc.jpg\" alt=\"tag ur self I'm the house\"></video><div class=\"media-caption entry-meta\">tag ur self I'm the house</div></li>","postedSingleVideoPage":true},{"id":"sports-carKIZtDoCJ","date":"2018-06-30T06:03:06.426Z","mediaFilename":"sports-carKIZtDoCJ.jpg","caption":"tag ur self I'm the sports car","postedToGit":true,"htmlFragment":"<li class=\"pane\">\n  <div class=\"time-stamp entry-meta\">\n    <a href=\"sports-carKIZtDoCJ.html\">\n      <time datetime=\"2018-06-30T06:03:06.426Z\">2018-6-30 06:03:06</time>\n    </a>\n  </div><img src=\"media/sports-carKIZtDoCJ.jpg\" alt=\"tag ur self I'm the sports car\"></video><div class=\"media-caption entry-meta\">tag ur self I'm the sports car</div></li>","postedSingleVideoPage":true},{"id":"rockOwdpLrWD","date":"2018-06-30T09:03:06.618Z","mediaFilename":"rockOwdpLrWD.jpg","caption":"tag ur self I'm the rock","postedToGit":true,"htmlFragment":"<li class=\"pane\">\n  <div class=\"time-stamp entry-meta\">\n    <a href=\"rockOwdpLrWD.html\">\n      <time datetime=\"2018-06-30T09:03:06.618Z\">2018-6-30 09:03:06</time>\n    </a>\n  </div><img src=\"media/rockOwdpLrWD.jpg\" alt=\"tag ur self I'm the rock\"></video><div class=\"media-caption entry-meta\">tag ur self I'm the rock</div></li>","postedSingleVideoPage":true},{"id":"leafakSjiVHY","date":"2018-06-30T12:03:06.693Z","mediaFilename":"leafakSjiVHY.jpg","caption":"tag ur self I'm the leaf","postedToGit":true,"htmlFragment":"<li class=\"pane\">\n  <div class=\"time-stamp entry-meta\">\n    <a href=\"leafakSjiVHY.html\">\n      <time datetime=\"2018-06-30T12:03:06.693Z\">2018-6-30 12:03:06</time>\n    </a>\n  </div><img src=\"media/leafakSjiVHY.jpg\" alt=\"tag ur self I'm the leaf\"></video><div class=\"media-caption entry-meta\">tag ur self I'm the leaf</div></li>","postedSingleVideoPage":true},{"id":"areajrcwMFMC","date":"2018-06-30T15:03:06.545Z","mediaFilename":"areajrcwMFMC.jpg","caption":"tag ur self I'm the area","postedToGit":true,"htmlFragment":"<li class=\"pane\">\n  <div class=\"time-stamp entry-meta\">\n    <a href=\"areajrcwMFMC.html\">\n      <time datetime=\"2018-06-30T15:03:06.545Z\">2018-6-30 15:03:06</time>\n    </a>\n  </div><img src=\"media/areajrcwMFMC.jpg\" alt=\"tag ur self I'm the area\"></video><div class=\"media-caption entry-meta\">tag ur self I'm the area</div></li>","postedSingleVideoPage":true},{"id":"treeDKjXGWTh","date":"2018-06-30T18:03:07.293Z","mediaFilename":"treeDKjXGWTh.jpg","caption":"tag ur self I'm the tree","postedToGit":true,"htmlFragment":"<li class=\"pane\">\n  <div class=\"time-stamp entry-meta\">\n    <a href=\"treeDKjXGWTh.html\">\n      <time datetime=\"2018-06-30T18:03:07.293Z\">2018-6-30 18:03:07</time>\n    </a>\n  </div><img src=\"media/treeDKjXGWTh.jpg\" alt=\"tag ur self I'm the tree\"></video><div class=\"media-caption entry-meta\">tag ur self I'm the tree</div></li>","postedSingleVideoPage":true},{"id":"flooringGOZRTapr","date":"2018-06-30T21:03:04.504Z","mediaFilename":"flooringGOZRTapr.jpg","caption":"tag ur self I'm the flooring","postedToGit":true,"htmlFragment":"<li class=\"pane\">\n  <div class=\"time-stamp entry-meta\">\n    <a href=\"flooringGOZRTapr.html\">\n      <time datetime=\"2018-06-30T21:03:04.504Z\">2018-6-30 21:03:04</time>\n    </a>\n  </div><img src=\"media/flooringGOZRTapr.jpg\" alt=\"tag ur self I'm the flooring\"></video><div class=\"media-caption entry-meta\">tag ur self I'm the flooring</div></li>","postedSingleVideoPage":true},{"id":"ferns-and-horsetailsgqArwErc","date":"2018-07-01T00:03:13.345Z","mediaFilename":"ferns-and-horsetailsgqArwErc.jpg","caption":"tag ur self I'm the ferns and horsetails","postedToGit":true,"htmlFragment":"<li class=\"pane\">\n  <div class=\"time-stamp entry-meta\">\n    <a href=\"ferns-and-horsetailsgqArwErc.html\">\n      <time datetime=\"2018-07-01T00:03:13.345Z\">2018-7-1 00:03:13</time>\n    </a>\n  </div><img src=\"media/ferns-and-horsetailsgqArwErc.jpg\" alt=\"tag ur self I'm the ferns and horsetails\"></video><div class=\"media-caption entry-meta\">tag ur self I'm the ferns and horsetails</div></li>","postedSingleVideoPage":true},{"id":"aerial-photographygKAFRYNt","date":"2018-07-01T06:03:04.835Z","mediaFilename":"aerial-photographygKAFRYNt.jpg","caption":"tag ur self I'm the aerial photography","postedToGit":true,"htmlFragment":"<li class=\"pane\">\n  <div class=\"time-stamp entry-meta\">\n    <a href=\"aerial-photographygKAFRYNt.html\">\n      <time datetime=\"2018-07-01T06:03:04.835Z\">2018-7-1 06:03:04</time>\n    </a>\n  </div><img src=\"media/aerial-photographygKAFRYNt.jpg\" alt=\"tag ur self I'm the aerial photography\"></video><div class=\"media-caption entry-meta\">tag ur self I'm the aerial photography</div></li>","postedSingleVideoPage":true},{"id":"monasterydMSIHGLX","date":"2018-07-01T09:03:06.819Z","mediaFilename":"monasterydMSIHGLX.jpg","caption":"tag ur self I'm the monastery","postedToGit":true,"htmlFragment":"<li class=\"pane\">\n  <div class=\"time-stamp entry-meta\">\n    <a href=\"monasterydMSIHGLX.html\">\n      <time datetime=\"2018-07-01T09:03:06.819Z\">2018-7-1 09:03:06</time>\n    </a>\n  </div><img src=\"media/monasterydMSIHGLX.jpg\" alt=\"tag ur self I'm the monastery\"></video><div class=\"media-caption entry-meta\">tag ur self I'm the monastery</div></li>","postedSingleVideoPage":true},{"id":"jointIDCFiZHp","date":"2018-07-01T12:03:06.851Z","mediaFilename":"jointIDCFiZHp.jpg","caption":"tag ur self I'm the joint","postedToGit":true,"htmlFragment":"<li class=\"pane\">\n  <div class=\"time-stamp entry-meta\">\n    <a href=\"jointIDCFiZHp.html\">\n      <time datetime=\"2018-07-01T12:03:06.851Z\">2018-7-1 12:03:06</time>\n    </a>\n  </div><img src=\"media/jointIDCFiZHp.jpg\" alt=\"tag ur self I'm the joint\"></video><div class=\"media-caption entry-meta\">tag ur self I'm the joint</div></li>","postedSingleVideoPage":true},{"id":"moths-and-butterfliesJSTZMxeJ","date":"2018-07-01T15:03:06.925Z","mediaFilename":"moths-and-butterfliesJSTZMxeJ.jpg","caption":"tag ur self I'm the moths and butterflies","postedToGit":true,"htmlFragment":"<li class=\"pane\">\n  <div class=\"time-stamp entry-meta\">\n    <a href=\"moths-and-butterfliesJSTZMxeJ.html\">\n      <time datetime=\"2018-07-01T15:03:06.925Z\">2018-7-1 15:03:06</time>\n    </a>\n  </div><img src=\"media/moths-and-butterfliesJSTZMxeJ.jpg\" alt=\"tag ur self I'm the moths and butterflies\"></video><div class=\"media-caption entry-meta\">tag ur self I'm the moths and butterflies</div></li>","postedSingleVideoPage":true},{"id":"housevxwMTzgj","date":"2018-07-01T18:03:07.037Z","mediaFilename":"housevxwMTzgj.jpg","caption":"tag ur self I'm the house","postedToGit":true,"htmlFragment":"<li class=\"pane\">\n  <div class=\"time-stamp entry-meta\">\n    <a href=\"housevxwMTzgj.html\">\n      <time datetime=\"2018-07-01T18:03:07.037Z\">2018-7-1 18:03:07</time>\n    </a>\n  </div><img src=\"media/housevxwMTzgj.jpg\" alt=\"tag ur self I'm the house\"></video><div class=\"media-caption entry-meta\">tag ur self I'm the house</div></li>","postedSingleVideoPage":true},{"id":"circlegoXpdKgk","date":"2018-07-01T21:03:09.080Z","mediaFilename":"circlegoXpdKgk.jpg","caption":"tag ur self I'm the circle","postedToGit":true,"htmlFragment":"<li class=\"pane\">\n  <div class=\"time-stamp entry-meta\">\n    <a href=\"circlegoXpdKgk.html\">\n      <time datetime=\"2018-07-01T21:03:09.080Z\">2018-7-1 21:03:09</time>\n    </a>\n  </div><img src=\"media/circlegoXpdKgk.jpg\" alt=\"tag ur self I'm the circle\"></video><div class=\"media-caption entry-meta\">tag ur self I'm the circle</div></li>","postedSingleVideoPage":true}]