[{"id":"ferrybbUgQWYB","date":"2018-11-08T15:03:28.421Z","mediaFilename":"ferrybbUgQWYB.jpg","caption":"tag ur self I'm the ferry","postedToGit":true,"htmlFragment":"<li class=\"pane\">\n  <div class=\"time-stamp entry-meta\">\n    <a href=\"ferrybbUgQWYB.html\">\n      <time datetime=\"2018-11-08T15:03:28.421Z\">2018-11-8 15:03:28</time>\n    </a>\n  </div><img src=\"media/ferrybbUgQWYB.jpg\" alt=\"tag ur self I'm the ferry\"></video><div class=\"media-caption entry-meta\">tag ur self I'm the ferry</div></li>","postedSingleVideoPage":true},{"id":"businessBybUqEiw","date":"2018-11-08T18:03:05.611Z","mediaFilename":"businessBybUqEiw.jpg","caption":"tag ur self I'm the business","postedToGit":true,"htmlFragment":"<li class=\"pane\">\n  <div class=\"time-stamp entry-meta\">\n    <a href=\"businessBybUqEiw.html\">\n      <time datetime=\"2018-11-08T18:03:05.611Z\">2018-11-8 18:03:05</time>\n    </a>\n  </div><img src=\"media/businessBybUqEiw.jpg\" alt=\"tag ur self I'm the business\"></video><div class=\"media-caption entry-meta\">tag ur self I'm the business</div></li>","postedSingleVideoPage":true},{"id":"flowering-plantMIkRtIaJ","date":"2018-11-08T21:03:06.981Z","mediaFilename":"flowering-plantMIkRtIaJ.jpg","caption":"tag ur self I'm the flowering plant","postedToGit":true,"htmlFragment":"<li class=\"pane\">\n  <div class=\"time-stamp entry-meta\">\n    <a href=\"flowering-plantMIkRtIaJ.html\">\n      <time datetime=\"2018-11-08T21:03:06.981Z\">2018-11-8 21:03:06</time>\n    </a>\n  </div><img src=\"media/flowering-plantMIkRtIaJ.jpg\" alt=\"tag ur self I'm the flowering plant\"></video><div class=\"media-caption entry-meta\">tag ur self I'm the flowering plant</div></li>","postedSingleVideoPage":true},{"id":"fruitYfIgXeZM","date":"2018-11-09T00:03:06.321Z","mediaFilename":"fruitYfIgXeZM.jpg","caption":"tag ur self I'm the fruit","postedToGit":true,"htmlFragment":"<li class=\"pane\">\n  <div class=\"time-stamp entry-meta\">\n    <a href=\"fruitYfIgXeZM.html\">\n      <time datetime=\"2018-11-09T00:03:06.321Z\">2018-11-9 00:03:06</time>\n    </a>\n  </div><img src=\"media/fruitYfIgXeZM.jpg\" alt=\"tag ur self I'm the fruit\"></video><div class=\"media-caption entry-meta\">tag ur self I'm the fruit</div></li>","postedSingleVideoPage":true},{"id":"cellseMtaLRar","date":"2018-11-09T03:03:23.385Z","mediaFilename":"cellseMtaLRar.jpg","caption":"tag ur self I'm \"cells\"","postedToGit":true,"htmlFragment":"<li class=\"pane\">\n  <div class=\"time-stamp entry-meta\">\n    <a href=\"cellseMtaLRar.html\">\n      <time datetime=\"2018-11-09T03:03:23.385Z\">2018-11-9 03:03:23</time>\n    </a>\n  </div><img src=\"media/cellseMtaLRar.jpg\" alt=\"tag ur self I'm \"cells\"\"></video><div class=\"media-caption entry-meta\">tag ur self I'm \"cells\"</div></li>","postedSingleVideoPage":true},{"id":"paperjWzTyyEL","date":"2018-11-09T06:03:05.920Z","mediaFilename":"paperjWzTyyEL.jpg","caption":"tag ur self I'm the paper","postedToGit":true,"htmlFragment":"<li class=\"pane\">\n  <div class=\"time-stamp entry-meta\">\n    <a href=\"paperjWzTyyEL.html\">\n      <time datetime=\"2018-11-09T06:03:05.920Z\">2018-11-9 06:03:05</time>\n    </a>\n  </div><img src=\"media/paperjWzTyyEL.jpg\" alt=\"tag ur self I'm the paper\"></video><div class=\"media-caption entry-meta\">tag ur self I'm the paper</div></li>","postedSingleVideoPage":true},{"id":"womanLrUsQDoy","date":"2018-11-09T09:03:07.124Z","mediaFilename":"womanLrUsQDoy.jpg","caption":"tag ur self I'm the woman","postedToGit":true,"htmlFragment":"<li class=\"pane\">\n  <div class=\"time-stamp entry-meta\">\n    <a href=\"womanLrUsQDoy.html\">\n      <time datetime=\"2018-11-09T09:03:07.124Z\">2018-11-9 09:03:07</time>\n    </a>\n  </div><img src=\"media/womanLrUsQDoy.jpg\" alt=\"tag ur self I'm the woman\"></video><div class=\"media-caption entry-meta\">tag ur self I'm the woman</div></li>","postedSingleVideoPage":true},{"id":"symmetryKPQUqIuI","date":"2018-11-09T12:03:05.964Z","mediaFilename":"symmetryKPQUqIuI.jpg","caption":"tag ur self I'm the symmetry","postedToGit":true,"htmlFragment":"<li class=\"pane\">\n  <div class=\"time-stamp entry-meta\">\n    <a href=\"symmetryKPQUqIuI.html\">\n      <time datetime=\"2018-11-09T12:03:05.964Z\">2018-11-9 12:03:05</time>\n    </a>\n  </div><img src=\"media/symmetryKPQUqIuI.jpg\" alt=\"tag ur self I'm the symmetry\"></video><div class=\"media-caption entry-meta\">tag ur self I'm the symmetry</div></li>","postedSingleVideoPage":true},{"id":"organismWtCEVYKV","date":"2018-11-09T15:03:05.442Z","mediaFilename":"organismWtCEVYKV.jpg","caption":"tag ur self I'm the organism","postedToGit":true,"htmlFragment":"<li class=\"pane\">\n  <div class=\"time-stamp entry-meta\">\n    <a href=\"organismWtCEVYKV.html\">\n      <time datetime=\"2018-11-09T15:03:05.442Z\">2018-11-9 15:03:05</time>\n    </a>\n  </div><img src=\"media/organismWtCEVYKV.jpg\" alt=\"tag ur self I'm the organism\"></video><div class=\"media-caption entry-meta\">tag ur self I'm the organism</div></li>","postedSingleVideoPage":true},{"id":"tourismPCtlqqTJ","date":"2018-11-09T18:03:05.327Z","mediaFilename":"tourismPCtlqqTJ.jpg","caption":"tag ur self I'm the tourism","postedToGit":true,"htmlFragment":"<li class=\"pane\">\n  <div class=\"time-stamp entry-meta\">\n    <a href=\"tourismPCtlqqTJ.html\">\n      <time datetime=\"2018-11-09T18:03:05.327Z\">2018-11-9 18:03:05</time>\n    </a>\n  </div><img src=\"media/tourismPCtlqqTJ.jpg\" alt=\"tag ur self I'm the tourism\"></video><div class=\"media-caption entry-meta\">tag ur self I'm the tourism</div></li>","postedSingleVideoPage":true},{"id":"competition-eventCLoqHaTd","date":"2018-11-09T21:03:05.262Z","mediaFilename":"competition-eventCLoqHaTd.jpg","caption":"tag ur self I'm the competition event","postedToGit":true,"htmlFragment":"<li class=\"pane\">\n  <div class=\"time-stamp entry-meta\">\n    <a href=\"competition-eventCLoqHaTd.html\">\n      <time datetime=\"2018-11-09T21:03:05.262Z\">2018-11-9 21:03:05</time>\n    </a>\n  </div><img src=\"media/competition-eventCLoqHaTd.jpg\" alt=\"tag ur self I'm the competition event\"></video><div class=\"media-caption entry-meta\">tag ur self I'm the competition event</div></li>","postedSingleVideoPage":true},{"id":"motor-vehiclezyjdCGTC","date":"2018-11-10T00:03:06.645Z","mediaFilename":"motor-vehiclezyjdCGTC.jpg","caption":"tag ur self I'm the motor vehicle","postedToGit":true,"htmlFragment":"<li class=\"pane\">\n  <div class=\"time-stamp entry-meta\">\n    <a href=\"motor-vehiclezyjdCGTC.html\">\n      <time datetime=\"2018-11-10T00:03:06.645Z\">2018-11-10 00:03:06</time>\n    </a>\n  </div><img src=\"media/motor-vehiclezyjdCGTC.jpg\" alt=\"tag ur self I'm the motor vehicle\"></video><div class=\"media-caption entry-meta\">tag ur self I'm the motor vehicle</div></li>","postedSingleVideoPage":true},{"id":"homeydiFmlLd","date":"2018-11-10T03:03:08.827Z","mediaFilename":"homeydiFmlLd.jpg","caption":"tag ur self I'm the home","postedToGit":true,"htmlFragment":"<li class=\"pane\">\n  <div class=\"time-stamp entry-meta\">\n    <a href=\"homeydiFmlLd.html\">\n      <time datetime=\"2018-11-10T03:03:08.827Z\">2018-11-10 03:03:08</time>\n    </a>\n  </div><img src=\"media/homeydiFmlLd.jpg\" alt=\"tag ur self I'm the home\"></video><div class=\"media-caption entry-meta\">tag ur self I'm the home</div></li>","postedSingleVideoPage":true},{"id":"girlpRRgJuWY","date":"2018-11-10T06:03:06.056Z","mediaFilename":"girlpRRgJuWY.jpg","caption":"tag ur self I'm the girl","postedToGit":true,"htmlFragment":"<li class=\"pane\">\n  <div class=\"time-stamp entry-meta\">\n    <a href=\"girlpRRgJuWY.html\">\n      <time datetime=\"2018-11-10T06:03:06.056Z\">2018-11-10 06:03:06</time>\n    </a>\n  </div><img src=\"media/girlpRRgJuWY.jpg\" alt=\"tag ur self I'm the girl\"></video><div class=\"media-caption entry-meta\">tag ur self I'm the girl</div></li>","postedSingleVideoPage":true}]